README.md
setup.py
aduck/__init__.py
aduck/error.py
aduck/error_codes.py
aduck.egg-info/PKG-INFO
aduck.egg-info/SOURCES.txt
aduck.egg-info/dependency_links.txt
aduck.egg-info/not-zip-safe
aduck.egg-info/top_level.txt
aduck/utils/__init__.py
aduck/utils/class_util.py
aduck/utils/collection_util.py
aduck/utils/df_util.py
aduck/utils/hash_util.py
aduck/utils/json_util.py
aduck/utils/metric_util.py
aduck/utils/rand_util.py
aduck/utils/rest_util.py
aduck/utils/sql_util.py
aduck/utils/table_json_utils.py
aduck/utils/time_util.py